{
  "about": "About",
  "alert": "Alert",
  "cancel": "Cancel",
  "close": "Close",
  "copyright": "Edequate &copy;2017-18 Edeqa",
  "default": "Default",
  "drawer_primary": "Main",
  "drawer_summary": "Summary",
  "drawer_main": "Main",
  "drawer_explore": "Products",
  "drawer_share": "Share",
  "drawer_resources": "Resources",
  "drawer_miscellaneous": "Miscellaneous",
  "drawer_settings": "Settings",
  "drawer_help": "Help",
  "drawer_last": "Last",
  "email": "E-mail",
  "english": "English",
  "error": "Error",
  "feedback": "Feedback",
  "help": "Help",
  "home": "Home",
  "info": "Information",
  "language": "Language",
  "legal_information": "Legal information",
  "loading": "Loading...",
  "ok": "OK",
  "no": "No",
  "page_not_found": "Page not found",
  "password": "Password",
  "privacy": "Privacy",
  "privacy_policy": "Privacy policy",
  "reload": "Reload",
  "russian": "Russian",
  "support": "Support",
  "terms": "Terms",
  "terms_of_service": "Terms of Service",
  "theme": "Theme",
  "title": "Edequate",
  "yes": "Yes"
}