{
  "about": "О сайте",
  "copyright": "Edequate &copy;2017-18 Edeqa",
  "drawer_primary": "Главная",
  "drawer_summary": "Сводка",
  "drawer_main": "Главная",
  "drawer_explore": "Продукты",
  "drawer_share": "Поделиться",
  "drawer_resources": "Ресурсы",
  "drawer_miscellaneous": "Разное",
  "drawer_settings": "Параметры",
  "drawer_help": "Справка",
  "drawer_last": "Последняя",
  "error": "Ошибка",
  "home": "Главная",
  "info": "Информация",
  "loading": "Загрузка...",
  "ok": "OK",
  "page_not_found": "Страница не найдена",
  "privacy": "Конфиденциальность",
  "privacy_policy": "Политика конфиденциальности",
  "title": "Edequate"
}